cuckoo/__init__.py
cuckoo/__main__.py
cuckoo/cuckoo.py
cuckoo/db.py
cuckoo/migration.py
cuckoo_db-0.2.2.dist-info/METADATA
cuckoo_db-0.2.2.dist-info/RECORD
cuckoo_db-0.2.2.dist-info/WHEEL
cuckoo_db-0.2.2.dist-info/entry_points.txt
cuckoo_db-0.2.2.dist-info/top_level.txt
