Metadata-Version: 2.1
Name: cuckoo-db
Version: 0.2.2
Summary: Simple migration tool
Home-page: https://github.com/opfront/cuckoo
Author: opfront
Author-email: dalloriam@gmail.com
License: MIT
Platform: UNKNOWN
Requires-Dist: fire
Requires-Dist: peewee
Requires-Dist: psycopg2-binary
